game_qu/__init__.py
game_qu/library_abstraction.py
game_qu/base/__init__.py
game_qu/base/colors.py
game_qu/base/count_event.py
game_qu/base/engines.py
game_qu/base/events.py
game_qu/base/file_reader.py
game_qu/base/fraction.py
game_qu/base/game_movement.py
game_qu/base/game_runner_function.py
game_qu/base/history_keeper.py
game_qu/base/id_creator.py
game_qu/base/important_constants.py
game_qu/base/important_variables.py
game_qu/base/keyboard.py
game_qu/base/library_changer.py
game_qu/base/library_independant_utility_functions.py
game_qu/base/lines.py
game_qu/base/paths.py
game_qu/base/quadratic_equations.py
game_qu/base/range.py
game_qu/base/timed_event.py
game_qu/base/unique_ids_list.py
game_qu/base/utility_functions.py
game_qu/base/velocity_calculator.py
game_qu/getting_started/__init__.py
game_qu/getting_started/getting_started.py
game_qu/getting_started/pong (example game).py
game_qu/gui_components/__init__.py
game_qu/gui_components/button.py
game_qu/gui_components/component.py
game_qu/gui_components/dimensions.py
game_qu/gui_components/grid.py
game_qu/gui_components/hud.py
game_qu/gui_components/intermediate_screen.py
game_qu/gui_components/navigation_screen.py
game_qu/gui_components/screen.py
game_qu/gui_components/text_box.py
game_qu/gui_components/window.py
game_qu/math/__init__.py
game_qu/math/bounded_function.py
game_qu/math/derivative.py
game_qu/math/function.py
game_qu/math/indefinite_integral.py
game_qu/math/line_segment.py
game_qu/math/linear_interpolation.py
game_qu/math/matrix.py
game_qu/math/physics_function.py
game_qu/math/piecewise_function.py
game_qu/math/point.py
game_qu/math/polynomial.py
game_qu/math/quadratic_function.py
game_qu/math/range.py
game_qu/math/vector_2d.py
game_qu/paths/__init__.py
game_qu/paths/action_followable_path.py
game_qu/paths/followable_path.py
game_qu/paths/physics_followable_path.py
game_qu/paths/piecewise_followable_path.py
game_qu/paths/velocity_followable_path.py
game_qu/pygame_abstraction/__init__.py
game_qu-2.1.3.dist-info/METADATA
game_qu-2.1.3.dist-info/WHEEL
game_qu-2.1.3.dist-info/RECORD
