Metadata-Version: 2.1
Name: game_qu
Version: 2.1.3
Project-URL: Homepage, https://github.com/codingspartan9/Game-Qu
Author-email: Micah Ribbens <mdribbens22@outlook.com>
Classifier: License :: OSI Approved :: MIT License
Classifier: Operating System :: OS Independent
Classifier: Programming Language :: Python :: 3
Requires-Python: >=3.7
